{
  "Name": "azure-ai-anomalydetector",
  "Version": "3.0.0-beta.5",
  "DevVersion": null,
  "DirectoryPath": "sdk/anomalydetector/azure-ai-anomalydetector",
  "ServiceDirectory": "anomalydetector",
  "ReadMePath": "sdk/anomalydetector/azure-ai-anomalydetector/README.md",
  "ChangeLogPath": "sdk/anomalydetector/azure-ai-anomalydetector/CHANGELOG.md",
  "Group": "com.azure",
  "SdkType": "client",
  "IsNewSdk": true,
  "ArtifactName": "azure-ai-anomalydetector",
  "ReleaseStatus": "2022-12-08",
  "Namespaces": [
    "com.azure.ai.anomalydetector",
    "com.azure.ai.anomalydetector.models"
  ]
}
