{
  "Name": "azure-storage-blob-batch",
  "Version": "12.25.1",
  "DevVersion": null,
  "DirectoryPath": "sdk/storage/azure-storage-blob-batch",
  "ServiceDirectory": "storage",
  "ReadMePath": "sdk/storage/azure-storage-blob-batch/README.md",
  "ChangeLogPath": "sdk/storage/azure-storage-blob-batch/CHANGELOG.md",
  "Group": "com.azure",
  "SdkType": "client",
  "IsNewSdk": true,
  "ArtifactName": "azure-storage-blob-batch",
  "ReleaseStatus": "2025-03-03",
  "IncludedForValidation": false,
  "AdditionalValidationPackages": [
    "com.azure:azure-storage-perf",
    "com.azure:perf-test-core"
  ],
  "ArtifactDetails": {
    "groupId": "com.azure",
    "safeName": "azurestorageblobbatch",
    "releaseInBatch": "${{ parameters.release_azurestorageblobbatch }}",
    "triggeringPaths": [
      "/sdk/storage/ci.yml"
    ],
    "name": "azure-storage-blob-batch"
  },
  "CIParameters": {
    "CIMatrixConfigs": [
      {
        "Name": "Storage_ci",
        "Path": "sdk/storage/platform-matrix-ci.json",
        "NonSparseParameters": "Agent",
        "GenerateVMJobs": true,
        "Selection": "sparse"
      }
    ]
  },
  "Namespaces": [
    "com.azure.storage.blob.batch",
    "com.azure.storage.blob.batch.options"
  ],
  "CIMatrixConfigs": [
    {
      "Name": "Storage_ci",
      "Path": "sdk/storage/platform-matrix-ci.json",
      "Selection": "sparse",
      "NonSparseParameters": "Agent",
      "GenerateVMJobs": true
    }
  ],
  "DependentPackages": null
}
