{
  "Name": "azure-resourcemanager",
  "Version": "2.48.0",
  "DevVersion": null,
  "DirectoryPath": "sdk/resourcemanager/azure-resourcemanager",
  "ServiceDirectory": "resourcemanager",
  "ReadMePath": "sdk/resourcemanager/azure-resourcemanager/README.md",
  "ChangeLogPath": "sdk/resourcemanager/azure-resourcemanager/CHANGELOG.md",
  "Group": "com.azure.resourcemanager",
  "SdkType": "mgmt",
  "IsNewSdk": true,
  "ArtifactName": "azure-resourcemanager",
  "ReleaseStatus": "2025-02-28",
  "IncludedForValidation": false,
  "AdditionalValidationPackages": [
    "com.azure.resourcemanager:azure-resourcemanager-samples",
    "com.azure.resourcemanager:azure-resourcemanager-perf",
    "com.azure.resourcemanager:azure-resourcemanager-test",
    "com.azure:perf-test-core"
  ],
  "ArtifactDetails": {
    "safeName": "azureresourcemanager",
    "name": "azure-resourcemanager",
    "triggeringPaths": [
      "/sdk/resourcemanager/ci.yml"
    ],
    "groupId": "com.azure.resourcemanager",
    "releaseInBatch": "${{ parameters.release_azureresourcemanager }}"
  },
  "CIParameters": {
    "CIMatrixConfigs": []
  },
  "Namespaces": [
    "com.azure.resourcemanager"
  ],
  "CIMatrixConfigs": [],
  "DependentPackages": null
}
