{
  "Name": "azure-resourcemanager-devtestlabs",
  "Version": "1.2.0-alpha.20250519.1",
  "DevVersion": "1.2.0-alpha.20250519.1",
  "DirectoryPath": "sdk/devtestlabs/azure-resourcemanager-devtestlabs",
  "ServiceDirectory": "devtestlabs",
  "ReadMePath": "sdk/devtestlabs/azure-resourcemanager-devtestlabs/README.md",
  "ChangeLogPath": "sdk/devtestlabs/azure-resourcemanager-devtestlabs/CHANGELOG.md",
  "Group": "com.azure.resourcemanager",
  "SdkType": "mgmt",
  "IsNewSdk": true,
  "ArtifactName": "azure-resourcemanager-devtestlabs",
  "ReleaseStatus": "Unreleased",
  "IncludedForValidation": false,
  "AdditionalValidationPackages": null,
  "ArtifactDetails": {
    "safeName": "azureresourcemanagerdevtestlabs",
    "groupId": "com.azure.resourcemanager",
    "triggeringPaths": [
      "/sdk/devtestlabs/ci.yml"
    ],
    "name": "azure-resourcemanager-devtestlabs"
  },
  "CIParameters": {
    "CIMatrixConfigs": []
  },
  "Namespaces": [
    "com.azure.resourcemanager.devtestlabs",
    "com.azure.resourcemanager.devtestlabs.fluent",
    "com.azure.resourcemanager.devtestlabs.fluent.models",
    "com.azure.resourcemanager.devtestlabs.models"
  ]
}
