{
  "Name": "azure-security-keyvault-certificates",
  "Version": "4.8.0-alpha.20250513.1",
  "DevVersion": "4.8.0-alpha.20250513.1",
  "DirectoryPath": "sdk/keyvault/azure-security-keyvault-certificates",
  "ServiceDirectory": "keyvault",
  "ReadMePath": "sdk/keyvault/azure-security-keyvault-certificates/README.md",
  "ChangeLogPath": "sdk/keyvault/azure-security-keyvault-certificates/CHANGELOG.md",
  "Group": "com.azure",
  "SdkType": "client",
  "IsNewSdk": true,
  "ArtifactName": "azure-security-keyvault-certificates",
  "ReleaseStatus": "Unreleased",
  "IncludedForValidation": false,
  "AdditionalValidationPackages": [
    "com.azure:azure-security-keyvault-perf",
    "com.azure:perf-test-core"
  ],
  "ArtifactDetails": {
    "groupId": "com.azure",
    "name": "azure-security-keyvault-certificates",
    "safeName": "azuresecuritykeyvaultcertificates",
    "releaseInBatch": "${{ parameters.release_azuresecuritykeyvaultcertificates }}",
    "triggeringPaths": [
      "/sdk/keyvault/ci.yml"
    ]
  },
  "CIParameters": {
    "CIMatrixConfigs": []
  },
  "Namespaces": [
    "com.azure.security.keyvault.certificates",
    "com.azure.security.keyvault.certificates.models"
  ]
}
